fr_common_lib/__init__.py
fr_common_lib/exc/__init__.py
fr_common_lib/exc/http.py
fr_common_lib/infra/__init__.py
fr_common_lib/infra/db/__init__.py
fr_common_lib/infra/db/providers/__init__.py
fr_common_lib/infra/db/providers/db_async.py
fr_common_lib/infra/db/providers/db_sync.py
fr_common_lib/infra/db/typed/__init__.py
fr_common_lib/infra/db/typed/async_session.py
fr_common_lib/infra/db/typed/config.py
fr_common_lib/infra/db/typed/sync_session.py
fr_common_lib/infra/jwt/__init__.py
fr_common_lib/infra/jwt/config.py
fr_common_lib/infra/jwt/exc.py
fr_common_lib/infra/jwt/provider.py
fr_common_lib/infra/jwt/schemas.py
fr_common_lib/infra/jwt/service.py
fr_common_lib/infra/kafka/__init__.py
fr_common_lib/infra/kafka/broker_settings.py
fr_common_lib/infra/kafka/client_settings.py
fr_common_lib/infra/kafka/faust.py
fr_common_lib/infra/redis/__init__.py
fr_common_lib/infra/redis/config.py
fr_common_lib/infra/redis/provider.py
fr_common_lib/infra/s3/__init__.py
fr_common_lib/infra/s3/client.py
fr_common_lib/infra/s3/container.py
fr_common_lib/infra/s3/manager.py
fr_common_lib/infra/s3/settings.py
fr_common_lib/infra/smtp/__init__.py
fr_common_lib/infra/smtp/config.py
fr_common_lib/infra/smtp/provider.py
fr_common_lib/infra/url_token/__init__.py
fr_common_lib/infra/url_token/config.py
fr_common_lib/infra/url_token/exc.py
fr_common_lib/infra/url_token/provider.py
fr_common_lib/infra/url_token/schemas.py
fr_common_lib/infra/url_token/service.py
fr_common_lib/py.typed
fr_common_lib/utils/__init__.py
fr_common_lib/utils/ioc_builder.py
fr_common_lib/utils/json_example.py
fr_common_lib/utils/pagination.py
fr_common_lib/utils/pd_load.py
fr_common_lib/utils/result.py
fr_common_lib-0.4.2.dist-info/METADATA
fr_common_lib-0.4.2.dist-info/WHEEL
fr_common_lib-0.4.2.dist-info/RECORD
